easypedidoapi/__init__.py
easypedidoapi/base.py
easypedidoapi/interfaces/__init__.py
easypedidoapi/interfaces/adatec.py
easypedidoapi-0.0.9.dist-info/METADATA
easypedidoapi-0.0.9.dist-info/WHEEL
easypedidoapi-0.0.9.dist-info/top_level.txt
easypedidoapi-0.0.9.dist-info/RECORD
